odoo/addons/l10n_it_sdi_channel/README.rst
odoo/addons/l10n_it_sdi_channel/__init__.py
odoo/addons/l10n_it_sdi_channel/__manifest__.py
odoo/addons/l10n_it_sdi_channel/data/mail_message_subtype_data.xml
odoo/addons/l10n_it_sdi_channel/i18n/it.po
odoo/addons/l10n_it_sdi_channel/i18n/l10n_it_sdi_channel.pot
odoo/addons/l10n_it_sdi_channel/models/__init__.py
odoo/addons/l10n_it_sdi_channel/models/account_move.py
odoo/addons/l10n_it_sdi_channel/models/company.py
odoo/addons/l10n_it_sdi_channel/models/fatturapa_attachment.py
odoo/addons/l10n_it_sdi_channel/models/fatturapa_attachment_out.py
odoo/addons/l10n_it_sdi_channel/models/sdi.py
odoo/addons/l10n_it_sdi_channel/readme/CONFIGURE.md
odoo/addons/l10n_it_sdi_channel/readme/CONTRIBUTORS.md
odoo/addons/l10n_it_sdi_channel/readme/DESCRIPTION.md
odoo/addons/l10n_it_sdi_channel/security/ir.model.access.csv
odoo/addons/l10n_it_sdi_channel/security/security.xml
odoo/addons/l10n_it_sdi_channel/static/description/icon.png
odoo/addons/l10n_it_sdi_channel/static/description/index.html
odoo/addons/l10n_it_sdi_channel/tests/__init__.py
odoo/addons/l10n_it_sdi_channel/tests/test_account_invoice.py
odoo/addons/l10n_it_sdi_channel/tests/test_fatturapa_attachment_out.py
odoo/addons/l10n_it_sdi_channel/views/account_move_views.xml
odoo/addons/l10n_it_sdi_channel/views/company_view.xml
odoo/addons/l10n_it_sdi_channel/views/fatturapa_attachment_views.xml
odoo/addons/l10n_it_sdi_channel/views/sdi_view.xml
odoo/addons/l10n_it_sdi_channel/wizards/__init__.py
odoo/addons/l10n_it_sdi_channel/wizards/send_to_sdi.py
odoo/addons/l10n_it_sdi_channel/wizards/send_to_sdi_views.xml
odoo_addon_l10n_it_sdi_channel-16.0.1.1.2.2.dist-info/METADATA
odoo_addon_l10n_it_sdi_channel-16.0.1.1.2.2.dist-info/WHEEL
odoo_addon_l10n_it_sdi_channel-16.0.1.1.2.2.dist-info/top_level.txt
odoo_addon_l10n_it_sdi_channel-16.0.1.1.2.2.dist-info/RECORD
